pjk/__init__.py
pjk/common.py
pjk/components.py
pjk/history.py
pjk/log.py
pjk/main.py
pjk/man_page.py
pjk/parser.py
pjk/progress.py
pjk/registry.py
pjk/usage.py
pjk/version.py
pjk/integrations/opensearch_client.py
pjk/integrations/opensearch_index_sink.py
pjk/integrations/opensearch_query_pipe.py
pjk/integrations/postgres_pipe.py
pjk/integrations/snowflake_pipe.py
pjk/pipes/__init__.py
pjk/pipes/denorm.py
pjk/pipes/factory.py
pjk/pipes/filter.py
pjk/pipes/head.py
pjk/pipes/join.py
pjk/pipes/let_reduce.py
pjk/pipes/map.py
pjk/pipes/move_field.py
pjk/pipes/progress_pipe.py
pjk/pipes/query_pipe.py
pjk/pipes/remove_field.py
pjk/pipes/sample.py
pjk/pipes/select.py
pjk/pipes/sort.py
pjk/pipes/tail.py
pjk/pipes/user_pipe_factory.py
pjk/pipes/where.py
pjk/sinks/__init__.py
pjk/sinks/create_sink.py
pjk/sinks/csv_sink.py
pjk/sinks/devnull.py
pjk/sinks/dir_sink.py
pjk/sinks/expect.py
pjk/sinks/factory.py
pjk/sinks/format_sink.py
pjk/sinks/graph.py
pjk/sinks/graph_bar_line.py
pjk/sinks/graph_cumulative.py
pjk/sinks/graph_hist.py
pjk/sinks/graph_scatter.py
pjk/sinks/json_sink.py
pjk/sinks/s3_sink.py
pjk/sinks/s3_stream.py
pjk/sinks/sinks.py
pjk/sinks/stdout.py
pjk/sinks/tsv_sink.py
pjk/sinks/user_sink_factory.py
pjk/sources/__init__.py
pjk/sources/csv_source.py
pjk/sources/dir_source.py
pjk/sources/factory.py
pjk/sources/favorite_source.py
pjk/sources/format_source.py
pjk/sources/inline_source.py
pjk/sources/json_source.py
pjk/sources/lazy_file.py
pjk/sources/lazy_file_local.py
pjk/sources/lazy_file_s3.py
pjk/sources/npy_source.py
pjk/sources/parquet_source.py
pjk/sources/s3_select_source.py
pjk/sources/s3_source.py
pjk/sources/source_list.py
pjk/sources/sql_source.py
pjk/sources/tsv_source.py
pjk/sources/user_source_factory.py
python_jack_knife-0.7.4.dist-info/licenses/LICENSE
python_jack_knife-0.7.4.dist-info/METADATA
python_jack_knife-0.7.4.dist-info/WHEEL
python_jack_knife-0.7.4.dist-info/entry_points.txt
python_jack_knife-0.7.4.dist-info/top_level.txt
python_jack_knife-0.7.4.dist-info/RECORD
