Metadata-Version: 2.4
Name: python-jack-knife
Version: 0.7.4
Summary: Python Jack Knife – a command line data processor
Author-email: Mike Schultz <mike.schultz@gmail.com>
License: 
Requires-Python: >=3.11
License-File: LICENSE
Requires-Dist: hjson>=3.1.0
Requires-Dist: pyyaml>=6.0
Requires-Dist: requests>=2.32.0
Provides-Extra: aws
Requires-Dist: boto3>=1.34; extra == "aws"
Provides-Extra: postgres
Requires-Dist: pg8000>=1.30.0; extra == "postgres"
Provides-Extra: parquet
Requires-Dist: pyarrow>=15.0.0; extra == "parquet"
Provides-Extra: plot
Requires-Dist: matplotlib>=3.9.0; extra == "plot"
Requires-Dist: pandas>=2.2.0; extra == "plot"
Provides-Extra: dev
Requires-Dist: pytest; extra == "dev"
Requires-Dist: black; extra == "dev"
Requires-Dist: ruff; extra == "dev"
Provides-Extra: all
Requires-Dist: boto3>=1.34; extra == "all"
Requires-Dist: pg8000>=1.30.0; extra == "all"
Requires-Dist: pyarrow>=15.0.0; extra == "all"
Requires-Dist: matplotlib>=3.9.0; extra == "all"
Requires-Dist: pandas>=2.2.0; extra == "all"
Requires-Dist: pytest; extra == "all"
Requires-Dist: black; extra == "all"
Requires-Dist: ruff; extra == "all"
Dynamic: license-file
